djtesting/__init__.py
djtesting/__version__.py
djtesting/cmdline.py
djtesting/exceptions.py
djtesting/request/__init__.py
djtesting/request/api.py
djtesting/request/build.py
djtesting/request/hooks.py
djtesting/request/log.py
djtesting/request/models.py
djtesting/request/utils/__init__.py
djtesting/request/utils/_allure.py
djtesting/request/utils/_assert.py
djtesting/request/utils/_objectpath.py
djtesting/request/utils/common.py
tests/__init__.py
tests/test_request_api.py
tests/test_request_models.py
djtesting-0.0.4.dist-info/METADATA
djtesting-0.0.4.dist-info/WHEEL
djtesting-0.0.4.dist-info/top_level.txt
djtesting-0.0.4.dist-info/RECORD
