Metadata-Version: 2.1
Name: djtesting
Version: 0.0.4
Summary: automated interface testing for business
Home-page: UNKNOWN
Author: chinablue
Author-email: chinablue@163.com
License: MIT
Platform: win10
Requires-Dist: requests
Requires-Dist: Faker
Requires-Dist: allure-pytest
Requires-Dist: objectpath
